onefactorauth/__init__.py
onefactorauth/__main__.py
onefactorauth/code.py
onefactorauth/config.py
onefactorauth-0.1.1.dist-info/LICENSE
onefactorauth-0.1.1.dist-info/METADATA
onefactorauth-0.1.1.dist-info/WHEEL
onefactorauth-0.1.1.dist-info/entry_points.txt
onefactorauth-0.1.1.dist-info/top_level.txt
onefactorauth-0.1.1.dist-info/RECORD
