Metadata-Version: 2.1
Name: onefactorauth
Version: 0.1.1
Summary: UNKNOWN
Home-page: https://github.com/r2dev2/onefactorauth
Author: Ronak Badhe
Author-email: ronak.badhe@gmail.com
License: UNKNOWN
Platform: UNKNOWN
Classifier: Programming Language :: Python :: 3
Classifier: License :: Public Domain
Classifier: Operating System :: OS Independent
Requires-Python: >=3.5
Requires-Dist: clipboard (==0.0.4)
Requires-Dist: requests (>=2.28.1)
